{
  "$schema": "https://schema.management.azure.com/schemas/2015-01-01/deploymentParameters.json#",
  "contentVersion": "1.0.0.0",
  "parameters": {
    "apiServiceName": {
      "value": "apiServiceName-dev"
    },
    "apiName": {
      "value": "demo-conference-api"
    },
    "operationName": {
      "value": "GetSessions"
    },
    "operationDisplayName": {
      "value": "GetSessions"
    },
    "operationDescription": {
      "value": "A list of sessions.  Optional parameters work as filters to reduce the listed sessions."
    },
    "httpMethod": {
      "value": "GET"
    },
    "urlSufix": {
      "value": "/sessions"
    },
    "policyFile": {
      "value": "<policies><inbound><base /></inbound><backend><base /></backend><outbound><base /></outbound><on-error><base /></on-error></policies>"
    }
  }
}
